{
  "packageId": "com.sven4321.telescopealign",
  "host": "s540d.github.io",
  "name": "Telescope Align",
  "launcherName": "Telescope Align",
  "display": "standalone",
  "themeColor": "#0A0A0A",
  "themeColorDark": "#000000",
  "navigationColor": "#000000",
  "navigationColorDark": "#000000",
  "navigationDividerColor": "#000000",
  "navigationDividerColorDark": "#000000",
  "backgroundColor": "#0A0A0A",
  "enableNotifications": true,
  "startUrl": "/CalibrateMyTelescope/",
  "iconUrl": "https://s540d.github.io/CalibrateMyTelescope/icons/icon-512.png",
  "maskableIconUrl": "https://s540d.github.io/CalibrateMyTelescope/icons/icon-512.png",
  "splashScreenFadeOutDuration": 300,
  "signingKey": {
    "path": "/Users/svenstrohkark/Documents/Programmierung/Projects/CalibrateMyTelescope/CalibrateMyTelescope/Android/keystore/telescopealign-release.keystore",
    "alias": "telescopealign"
  },
  "appVersionName": "1.0.0",
  "appVersionCode": 1,
  "shortcuts": [],
  "generatorApp": "unknown",
  "webManifestUrl": "https://s540d.github.io/CalibrateMyTelescope/manifest.webmanifest",
  "fallbackType": "customtabs",
  "features": {},
  "alphaDependencies": {
    "enabled": false
  },
  "enableSiteSettingsShortcut": true,
  "isChromeOSOnly": false,
  "isMetaQuest": false,
  "fullScopeUrl": "https://s540d.github.io/CalibrateMyTelescope/",
  "minSdkVersion": 21,
  "orientation": "portrait",
  "fingerprints": [],
  "additionalTrustedOrigins": [],
  "retainedBundles": [],
  "protocolHandlers": [],
  "fileHandlers": [],
  "launchHandlerClientMode": "",
  "displayOverride": [],
  "appVersion": "1.0.0"
}
